mapsnap
