Metadata-Version: 2.1
Name: mapsnap
Version: 1.0.1
Summary: Apple Maps Web Snapshots on Python
Home-page: https://mapsnap.ygor.dev
Author: Ygor Lemos
Author-email: ygbr@mac.com
License: MIT
Download-URL: https://github.com/ygbr/mapsnap/releases/latest
Project-URL: Bug Tracker, https://github.com/ygbr/mapsnap/issues
Project-URL: Documentation, https://mapsnap.ygor.dev
Project-URL: Source Code, https://github.com/ygbr/mapsnap
Keywords: apple,mapkit,web,snapshot,maps,map
Platform: any
Classifier: Development Status :: 4 - Beta
Classifier: Intended Audience :: Developers
Classifier: Intended Audience :: Science/Research
Classifier: Intended Audience :: Information Technology
Classifier: Intended Audience :: System Administrators
Classifier: Intended Audience :: Telecommunications Industry
Classifier: License :: OSI Approved :: MIT License
Classifier: Operating System :: OS Independent
Classifier: Topic :: Software Development :: Libraries
Classifier: Topic :: Software Development :: Libraries :: Python Modules
Classifier: Topic :: Internet
Classifier: Topic :: Internet :: WWW/HTTP :: Dynamic Content
Classifier: Topic :: Internet :: WWW/HTTP :: Indexing/Search
Classifier: Topic :: Multimedia
Classifier: Topic :: Other/Nonlisted Topic
Classifier: Topic :: Scientific/Engineering
Classifier: Topic :: Scientific/Engineering :: GIS
Classifier: Topic :: Scientific/Engineering :: Image Processing
Classifier: Topic :: Scientific/Engineering :: Visualization
Classifier: Topic :: Utilities
Classifier: Typing :: Typed
Classifier: Programming Language :: Python
Classifier: Programming Language :: Python :: 3
Classifier: Programming Language :: Python :: 3.7
Classifier: Programming Language :: Python :: 3.8
Requires-Python: >=3.7
